{
  "description": "项目配置文件。",
  "setting": {
    "urlCheck": true,
    "es6": true,
    "enhance": false,
    "postcss": true,
    "preloadBackgroundData": false,
    "minified": false,
    "newFeature": false,
    "coverView": true,
    "nodeModules": false,
    "autoAudits": false,
    "showShadowRootInWxmlPanel": true,
    "scopeDataCheck": false,
    "uglifyFileName": false,
    "checkInvalidKey": true,
    "checkSiteMap": true,
    "uploadWithSourceMap": true,
    "compileHotReLoad": false,
    "useMultiFrameRuntime": false,
    "useApiHook": true,
    "babelSetting": {
      "ignore": [],
      "disablePlugins": [],
      "outputPath": ""
    },
    "enableEngineNative": false,
    "useIsolateContext": true,
    "useCompilerModule": true,
    "userConfirmedUseCompilerModuleSwitch": false,
    "packNpmManually": false,
    "packNpmRelationList": [],
    "minifyWXSS": true
  },
  "compileType": "game",
  "libVersion": "game",
  "appid": "wx145d2d2fd86cb853",
  "projectname": "hello_world",
  "simulatorType": "wechat",
  "simulatorPluginLibVersion": {},
  "condition": {
    "search": {
      "list": []
    },
    "conversation": {
      "list": []
    },
    "game": {
      "currentL": -1,
      "list": []
    },
    "miniprogram": {
      "list": []
    }
  }
}